fastvector/__init__.py
fastvector/vector.py
fastvector/version.py
fastvector-5.1.0.dist-info/LICENSE
fastvector-5.1.0.dist-info/METADATA
fastvector-5.1.0.dist-info/WHEEL
fastvector-5.1.0.dist-info/top_level.txt
fastvector-5.1.0.dist-info/RECORD
